ecm/__init__.py
ecm/colors.py
ecm/cost_function.py
ecm/errors.py
ecm/html_writer.py
ecm/kegg_model.py
ecm/model.py
ecm/optimized_bottleneck_driving_force.py
ecm/sbtab_multi.py
ecm/simulator.py
ecm/util.py
enzyme_cost_minimization-0.1.2.dist-info/LICENSE
enzyme_cost_minimization-0.1.2.dist-info/METADATA
enzyme_cost_minimization-0.1.2.dist-info/WHEEL
enzyme_cost_minimization-0.1.2.dist-info/top_level.txt
enzyme_cost_minimization-0.1.2.dist-info/RECORD
