Metadata-Version: 2.1
Name: enzyme-cost-minimization
Version: 0.1.2
Summary: eQuilibrator API - A command-line API with minimal dependencies for calculation of standard thermodynamic potentials of biochemical reactions using the data found on eQuilibrator. Does not require any network connections.
Home-page: https://github.com/eladnoor/enzyme-cost
Author: Elad Noor
Author-email: noor@imsb.biol.ethz.ch
License: MIT
Platform: UNKNOWN
Classifier: Development Status :: 4 - Beta
Classifier: Intended Audience :: Science/Research
Classifier: Topic :: Scientific/Engineering :: Chemistry
Classifier: License :: OSI Approved :: MIT License
Classifier: Programming Language :: Python :: 3.6
Requires-Dist: numpy (>=1.15.2)
Requires-Dist: scipy (>=1.1.0)
Requires-Dist: pulp (>=1.6.8)
Requires-Dist: pandas (>=0.23.4)
Requires-Dist: sbtab (>=0.9.27)
Requires-Dist: matplotlib (>=3.0.0)
Requires-Dist: equilibrator-api (>=0.1.1)
